leet/__init__.py
leet/api.py
leet/auth.py
leet/problems.py
leet/runner.py
leet/submit.py
leetcli/__init__.py
leetcli/main.py
leetcode_terminal-0.1.5.dist-info/METADATA
leetcode_terminal-0.1.5.dist-info/WHEEL
leetcode_terminal-0.1.5.dist-info/entry_points.txt
leetcode_terminal-0.1.5.dist-info/top_level.txt
leetcode_terminal-0.1.5.dist-info/RECORD
