Metadata-Version: 2.4
Name: leetcode-terminal
Version: 0.1.5
Summary: LeetCLI - Solve, practice, and fetch LeetCode challenges from your terminal
Home-page: https://github.com/Chitransh2309
Author: Chitransh Saxena
Author-email: geniussaxena007@gmail.com
Classifier: Programming Language :: Python :: 3
Classifier: License :: OSI Approved :: MIT License
Classifier: Operating System :: OS Independent
Classifier: Environment :: Console
Classifier: Topic :: Utilities
Requires-Python: >=3.7
Requires-Dist: typer[all]>=0.9.0
Requires-Dist: requests>=2.30.0
Requires-Dist: rich>=13.0.0
Requires-Dist: html2text
Dynamic: author
Dynamic: author-email
Dynamic: classifier
Dynamic: description
Dynamic: description-content-type
Dynamic: home-page
Dynamic: requires-dist
Dynamic: requires-python
Dynamic: summary
